ld2410_ble/__init__.py
ld2410_ble/const.py
ld2410_ble/exceptions.py
ld2410_ble/ld2410_ble.py
ld2410_ble/models.py
ld2410_ble/py.typed
ld2410_ble-0.2.0.dist-info/METADATA
ld2410_ble-0.2.0.dist-info/WHEEL
ld2410_ble-0.2.0.dist-info/LICENSE
ld2410_ble-0.2.0.dist-info/RECORD
